lanectl/__init__.py
lanectl/blocks.py
lanectl/engine.py
lanectl/inject.py
lanectl/py.typed
lanectl/utils.py
lanectl-0.4.0.dist-info/licenses/LICENSE
lanectl-0.4.0.dist-info/METADATA
lanectl-0.4.0.dist-info/WHEEL
lanectl-0.4.0.dist-info/top_level.txt
lanectl-0.4.0.dist-info/RECORD
