Metadata-Version: 2.4
Name: lanectl
Version: 0.4.0
Summary: embed scripting engine by Infrared LLC.
Home-page: https://github.com/infraredhuh/lanectl
Author: infrared
Author-email: faneorg.official@gmail.com
Classifier: Programming Language :: Python :: 3
Classifier: License :: OSI Approved :: MIT License
Classifier: Operating System :: OS Independent
Classifier: Typing :: Typed
Requires-Python: >=3.8
License-File: LICENSE
Requires-Dist: discord.py
Dynamic: author
Dynamic: author-email
Dynamic: classifier
Dynamic: description
Dynamic: description-content-type
Dynamic: home-page
Dynamic: license-file
Dynamic: requires-dist
Dynamic: requires-python
Dynamic: summary
